linkis_python_sdk/__init__.py
linkis_python_sdk/client.py
linkis_python_sdk/asyncio/__init__.py
linkis_python_sdk/asyncio/client.py
linkis_python_sdk/config/__init__.py
linkis_python_sdk/config/config.py
linkis_python_sdk/core/__init__.py
linkis_python_sdk/core/data_resolve.py
linkis_python_sdk/model/__init__.py
linkis_python_sdk/model/model.py
linkis_python_sdk-0.2.0.dist-info/licenses/LICENSE
linkis_python_sdk-0.2.0.dist-info/METADATA
linkis_python_sdk-0.2.0.dist-info/WHEEL
linkis_python_sdk-0.2.0.dist-info/top_level.txt
linkis_python_sdk-0.2.0.dist-info/RECORD
