Metadata-Version: 2.4
Name: linkis-python-sdk
Version: 0.2.0
Summary: Python SDK for Linkis Service
Home-page: https://github.com/huangli1279/linkis-python-sdk
Author: rogerhuang
Author-email: haungli1279@163.com
Project-URL: Bug Tracker, https://github.com/huangli1279/linkis-python-sdk/issues
Classifier: Programming Language :: Python :: 3
Classifier: License :: OSI Approved :: Apache Software License
Classifier: Operating System :: OS Independent
Requires-Python: >=3.9
License-File: LICENSE
Requires-Dist: requests>=2.25.0
Requires-Dist: pandas>=1.0.0
Requires-Dist: redis>=4.0.0
Requires-Dist: aiohttp>=3.7.0
Dynamic: author
Dynamic: author-email
Dynamic: classifier
Dynamic: description
Dynamic: description-content-type
Dynamic: home-page
Dynamic: license-file
Dynamic: project-url
Dynamic: requires-dist
Dynamic: requires-python
Dynamic: summary
